SpeakingJavascript/README.md
SpeakingJavascript/__init__.py
SpeakingJavascript/__main__.py
SpeakingJavascript/file.epub
SpeakingJavascript/index.html
SpeakingJavascript/css/__init__.py
SpeakingJavascript/css/annotations.css
SpeakingJavascript/css/main.css
SpeakingJavascript/css/normalize.css
SpeakingJavascript/css/popup.css
SpeakingJavascript/font/__init__.py
SpeakingJavascript/font/fontello.eot
SpeakingJavascript/font/fontello.svg
SpeakingJavascript/font/fontello.ttf
SpeakingJavascript/font/fontello.woff
SpeakingJavascript/img/__init__.py
SpeakingJavascript/img/annotator-glyph-sprite.png
SpeakingJavascript/img/annotator-icon-sprite.png
SpeakingJavascript/img/apple-touch-icon.png
SpeakingJavascript/img/cancelfullscreen.png
SpeakingJavascript/img/close.png
SpeakingJavascript/img/fullscreen.png
SpeakingJavascript/img/loader.gif
SpeakingJavascript/img/menu-icon.png
SpeakingJavascript/img/save.png
SpeakingJavascript/img/saved.png
SpeakingJavascript/img/settings-s.png
SpeakingJavascript/img/settings.png
SpeakingJavascript/img/star.png
SpeakingJavascript/js/__init__.py
SpeakingJavascript/js/epub.js
SpeakingJavascript/js/epub.min.js
SpeakingJavascript/js/epub.min.map
SpeakingJavascript/js/hooks.min.js
SpeakingJavascript/js/hooks.min.map
SpeakingJavascript/js/reader.js
SpeakingJavascript/js/reader.js.map
SpeakingJavascript/js/reader.min.js
SpeakingJavascript/js/reader.min.map
SpeakingJavascript/js/hooks/__init__.py
SpeakingJavascript/js/hooks/extensions/__init__.py
SpeakingJavascript/js/hooks/extensions/highlight.js
SpeakingJavascript/js/libs/__init__.py
SpeakingJavascript/js/libs/jquery.min.js
SpeakingJavascript/js/libs/localforage.min.js
SpeakingJavascript/js/libs/screenfull.js
SpeakingJavascript/js/libs/screenfull.min.js
SpeakingJavascript/js/libs/zip.min.js
SpeakingJavascript/js/plugins/__init__.py
SpeakingJavascript/js/plugins/hypothesis.js
SpeakingJavascript/js/plugins/search.js
speaking_javascript-2024.3.2.0.dist-info/METADATA
speaking_javascript-2024.3.2.0.dist-info/WHEEL
speaking_javascript-2024.3.2.0.dist-info/entry_points.txt
speaking_javascript-2024.3.2.0.dist-info/top_level.txt
speaking_javascript-2024.3.2.0.dist-info/RECORD
